cpt_python/__init__.py
cpt_python/const.py
cpt_python/cpt_python.py
cpt_python-0.0.2.dist-info/METADATA
cpt_python-0.0.2.dist-info/WHEEL
cpt_python-0.0.2.dist-info/licenses/LICENSE
cpt_python-0.0.2.dist-info/RECORD
